improved_json/__init__.py
improved_json/code.py
improved_json/improved_json.py
improved_json/py.typed
improved_json/type_check.py
improved_json/types.py
improved_json-2.1.0.dist-info/LICENSE
improved_json-2.1.0.dist-info/METADATA
improved_json-2.1.0.dist-info/WHEEL
improved_json-2.1.0.dist-info/top_level.txt
improved_json-2.1.0.dist-info/RECORD
