Metadata-Version: 2.1
Name: improved_json
Version: 2.1.0
Summary: A small add-on for python's builtin json library
License: GPL
Project-URL: Homepage, https://github.com/zwimer/improved_json
Classifier: Programming Language :: Python :: 3
Classifier: Programming Language :: Python :: 3.10
Requires-Python: >=3.10
License-File: LICENSE
Requires-Dist: simple-type-checker >=2.2.0
